mountaineer_bot/__init__.py
mountaineer_bot/api.py
mountaineer_bot/core.py
mountaineer_bot/list_profile.py
mountaineer_bot/list_redemptions.py
mountaineer_bot/main.py
mountaineer_bot/security.py
mountaineer_bot/setup.py
mountaineer_bot/utils.py
mountaineer_bot/windows_auth.py
mountaineer_bot/bots/__init__.py
mountaineer_bot/bots/add_bot.py
mountaineer_bot/bots/mod_bot.py
mountaineer_bot/bots/mountaineers_bot.py
mountaineer_bot/bots/novae_bot.py
mountaineer_bot/bots/novae_bot2.py
mountaineer_bot/bots/streamer_bot.py
mountaineer_bot/bots/test_bot.py
mountaineer_bot/components/__init__.py
mountaineer_bot/components/count_down.py
mountaineer_bot/components/first_identifier.py
mountaineer_bot/components/level_adder.py
mountaineer_bot/components/scheduler.py
mountaineer_bot/components/sound_reactor.py
mountaineer_bot/components/stream_live.py
mountaineer_bot/components/text_command.py
mountaineer_bot/data/env.cfg
mountaineer_bot/tw_events/__init__.py
mountaineer_bot/tw_events/core.py
mountaineer_bot/tw_events/scopes.py
mountaineer_bot/tw_events/types/__init__.py
mountaineer_bot/tw_events/types/base_messages.py
mountaineer_bot/tw_events/types/core.py
mountaineer_bot/tw_events/types/messages.py
mountaineer_bot/twitch_auth/__init__.py
mountaineer_bot/twitch_auth/core.py
mountaineer_bot/twitch_auth/device_flow.py
mountaineer_bot-0.1.2.dist-info/LICENSE.txt
mountaineer_bot-0.1.2.dist-info/METADATA
mountaineer_bot-0.1.2.dist-info/WHEEL
mountaineer_bot-0.1.2.dist-info/top_level.txt
mountaineer_bot-0.1.2.dist-info/RECORD
