Metadata-Version: 2.2
Name: mountaineer_bot
Version: 0.1.2
Summary: Wrapper for pre-rolled bot templates for Twitch
License:  GNU AFFERO GENERAL PUBLIC LICENSE
Classifier: Development Status :: 3 - Alpha
Classifier: Intended Audience :: Developers
Classifier: Topic :: Communications :: Chat
Classifier: License :: OSI Approved :: GNU Affero General Public License v3 or later (AGPLv3+)
Classifier: Programming Language :: Python :: 3
Classifier: Programming Language :: Python :: 3.10
Classifier: Programming Language :: Python :: 3.11
Classifier: Programming Language :: Python :: 3.12
Classifier: Programming Language :: Python :: 3.13
Requires-Python: >=3.10
License-File: LICENSE.txt
Requires-Dist: twitchio>=2.6.0
Requires-Dist: twitchAPI>=3.10.0
Requires-Dist: keyring>=23.13.1
Requires-Dist: requests>=2.30.0
Requires-Dist: flask>=2.3.2
Requires-Dist: pytz>=2023.3
Requires-Dist: tzlocal>=5.2
Requires-Dist: appdirs>=1.4.4
Requires-Dist: websockets>=14.1
Requires-Dist: pyyaml>=6.0.2
Requires-Dist: playsound==1.2.2
